[
    {
        "id": 1,
        "image": "/assets/Artanis.jpg",
        "clicked": false
    },
    {
        "id": 2,
        "image": "/assets/Arthas.jpg",
        "clicked": false
    },
    {
        "id": 3,
        "image": "/assets/Diablo.jpg",
        "clicked": false
    },
    {
        "id": 4,
        "image": "/assets/Greymane.jpg",
        "clicked": false
    },
    {
        "id": 5,
        "image": "/assets/Kerrigan.jpg",
        "clicked": false
    },
    {
        "id": 6,
        "image": "/assets/Mathael.jpg",
        "clicked": false
    },
    {
        "id": 7,
        "image": "/assets/Raynor.jpg",
        "clicked": false
    },
    {
        "id": 8,
        "image": "/assets/Thrall.jpg",
        "clicked": false
    },
    {
        "id": 9,
        "image": "/assets/Tyrael.jpg",
        "clicked": false
    }
]